pyheart.py
pyheart-0.0.5.dist-info/DESCRIPTION.rst
pyheart-0.0.5.dist-info/METADATA
pyheart-0.0.5.dist-info/RECORD
pyheart-0.0.5.dist-info/WHEEL
pyheart-0.0.5.dist-info/metadata.json
pyheart-0.0.5.dist-info/top_level.txt
